prqrs-0.1.0.dist-info/METADATA
prqrs-0.1.0.dist-info/WHEEL
prqrs-0.1.0.dist-info/license_files/LICENSE.txt
prqrs/__init__.py
prqrs/prqrs.cpython-311-darwin.so
prqrs-0.1.0.dist-info/RECORD
