Metadata-Version: 2.1
Name: prqrs
Version: 0.1.0
Classifier: License :: OSI Approved :: MIT License
Classifier: Programming Language :: Rust
Classifier: Programming Language :: Python :: Implementation :: CPython
Classifier: Programming Language :: Python :: Implementation :: PyPy
License-File: LICENSE.txt
Summary: Benchmarked priority queue implementation in Rust
Keywords: priority queue,pyo3
Author-email: Louis Maddox <louismmx@gmail.com>
License: MIT
Requires-Python: >=3.10, <3.12
